flask_mvc/__init__.py
flask_mvc/__version__.py
flask_mvc/cli.py
flask_mvc/core/__init__.py
flask_mvc/core/config.py
flask_mvc/core/exceptions.py
flask_mvc/core/file_handler.py
flask_mvc/core/generators.py
flask_mvc/core/name_utils.py
flask_mvc/core/template_renderer.py
flask_mvc/flask_mvc.py
flask_mvc/helpers/html/input_method_helper.py
flask_mvc/middlewares/blueprint_middleware.py
flask_mvc/middlewares/callback_middleware.py
flask_mvc/middlewares/http/namespace_middleware.py
flask_mvc/middlewares/http/router_middleware.py
flask_mvc/templates/base_controller.jinja2
flask_mvc2-0.1.0.dist-info/LICENSE
flask_mvc2-0.1.0.dist-info/METADATA
flask_mvc2-0.1.0.dist-info/WHEEL
flask_mvc2-0.1.0.dist-info/entry_points.txt
flask_mvc2-0.1.0.dist-info/RECORD
