Metadata-Version: 2.3
Name: flask-mvc2
Version: 0.1.0
Summary: Transform Flask into a structured MVC architecture with powerful CLI tools
License: MIT
Keywords: flask,mvc,web-framework,cli,generator,architecture,flask-extension,scaffold,crud,rest-api
Author: Marcus Pereira
Author-email: marcus@negros.dev
Maintainer: Marcus Pereira
Maintainer-email: marcus@negros.dev
Requires-Python: >=3.10,<4.0
Classifier: Development Status :: 5 - Production/Stable
Classifier: Environment :: Web Environment
Classifier: Framework :: Flask
Classifier: Intended Audience :: Developers
Classifier: License :: OSI Approved :: MIT License
Classifier: Operating System :: OS Independent
Classifier: Programming Language :: Python :: 3
Classifier: Programming Language :: Python :: 3.10
Classifier: Programming Language :: Python :: 3.11
Classifier: Programming Language :: Python :: 3.12
Classifier: Programming Language :: Python :: 3.13
Classifier: Topic :: Internet :: WWW/HTTP :: Dynamic Content
Classifier: Topic :: Software Development :: Code Generators
Classifier: Topic :: Software Development :: Libraries :: Python Modules
Requires-Dist: Flask (>=3.0.0,<4.0.0)
Requires-Dist: Jinja2 (>=3.1.0,<4.0.0)
Requires-Dist: click (>=8.0.0,<9.0.0)
Requires-Dist: method-override (>=0.3.0,<0.4.0)
Project-URL: Documentation, https://marcuxyz.github.io/flask-mvc
Project-URL: Homepage, https://github.com/marcuxyz/flask-mvc
Project-URL: Repository, https://github.com/marcuxyz/flask-mvc
